<ModelBehaviors>
	<Include RelativeFile="Subtemplates\\Passenger_Subtemplates.xml"/>
	<!-- Passenger ############################################## -->
	<Template Name="ASOBO_PASSENGER_Switch_Cabin_Heat_Template">
		<UseTemplate Name="ASOBO_PASSENGER_Switch_Cabin_Heat_SubTemplate">
		</UseTemplate>
	</Template>

	<Template Name="ASOBO_PASSENGER_Switch_Cabin_Air_Template">
		<UseTemplate Name="ASOBO_PASSENGER_Switch_Cabin_Air_SubTemplate">
		</UseTemplate>
	</Template>

	<Template Name="ASOBO_PASSENGER_Switch_Climate_Template">
		<Component ID="#NODE_ID#" Node="#NODE_ID#">
			<UseTemplate Name="ASOBO_GT_Switch_3States">
				<SWITCH_POSITION_VAR>CLIMATE_CONTROL</SWITCH_POSITION_VAR>
				<SWITCH_POSITION_TYPE>L</SWITCH_POSITION_TYPE>
				<COUNT>3</COUNT>
				<CODE_POS_0>
					(* OFF *) 0
				</CODE_POS_0>
				<CODE_POS_1>
					(* NORM *) 1
				</CODE_POS_1>
				<CODE_POS_2>
					(* COMP ON *) 2
				</CODE_POS_2>
			</UseTemplate>
		</Component>
	</Template>

	<Template Name="ASOBO_PASSENGER_Switch_PRESSOURCE_Template">
		<Component ID="#NODE_ID#" Node="#NODE_ID#">
			<UseTemplate Name="ASOBO_GT_Update">
				<UPDATE_ONCE>True</UPDATE_ONCE>
				<UPDATE_CODE>
                2 (&gt;L:PRESSOURCE) 					<!-- Set default -->
				</UPDATE_CODE>
			</UseTemplate>
			<UseTemplate Name="ASOBO_GT_Switch_5States">
				<SWITCH_POSITION_VAR>PRESSOURCE</SWITCH_POSITION_VAR>
				<SWITCH_POSITION_TYPE>L</SWITCH_POSITION_TYPE>
				<COUNT>5</COUNT>
				<CODE_POS_0>
				(* OFF *) 0
				</CODE_POS_0>
				<CODE_POS_1>
				(* LEFT *) 1
				</CODE_POS_1>
				<CODE_POS_2>
				(* NORM *) 2
				</CODE_POS_2>
				<CODE_POS_3>
				(* RIGHT *) 3
				</CODE_POS_3>
				<CODE_POS_4>
				(* FRESH *) 4
				</CODE_POS_4>
			</UseTemplate>
		</Component>
	</Template>
</ModelBehaviors>